<?xml version="1.0" encoding="UTF-8"?>
<ESCENARIO anchoPX="800" altoPX="600" maxJugadores="4">
	<FONDO>
		<CAPAS cantidad="3">
			<IMAGEN nombre="fondocieloScene2.bmp" zIndex="2" width="2600" height="600"/>
			<IMAGEN nombre="objetosScene2.bmp" zIndex="1" width="1300" height="600"/>
			<IMAGEN nombre="fondoScene2.bmp" zIndex="3" width="1820" height="600"/>
		</CAPAS>
	</FONDO>
	<SPRITES cantidad="6">
		<SPRITE id="PlayerRed" frameWidth="37" frameHeight="41">
				<ESTADOS cantidad="11">
					<ESTADO id="QUIETO-DER" cantFrames="3"/>
					<ESTADO id="CAMINA-DER" cantFrames="9"/>
					<ESTADO id="DESCONECTADO" cantFrames="1"/>
					<ESTADO id="AGACHADO" cantFrames="2"/>
					<ESTADO id="SALTANDO" cantFrames="3"/>
					<ESTADO id="CAMINA-IZQ" cantFrames="9"/>
					<ESTADO id="SALTANDO-DER" cantFrames="3"/>
					<ESTADO id="SALTANDO-IZQ" cantFrames="3"/>
					<ESTADO id="QUIETO-IZQ" cantFrames="3"/>
					<ESTADO id="DISPARA-DER" cantFrames="2"/>
					<ESTADO id="DISPARA-IZQ" cantFrames="2"/>
				</ESTADOS>
		</SPRITE>
		<SPRITE id="PlayerYellow" frameWidth="37" frameHeight="41">
				<ESTADOS cantidad="9">
					<ESTADO id="QUIETO-DER" cantFrames="3"/>
					<ESTADO id="CAMINA-DER" cantFrames="9"/>
					<ESTADO id="DESCONECTADO" cantFrames="1"/>
					<ESTADO id="AGACHADO" cantFrames="2"/>
					<ESTADO id="SALTANDO" cantFrames="3"/>
					<ESTADO id="CAMINA-IZQ" cantFrames="9"/>
					<ESTADO id="SALTANDO-DER" cantFrames="3"/>
					<ESTADO id="SALTANDO-IZQ" cantFrames="3"/>
					<ESTADO id="QUIETO-IZQ" cantFrames="3"/>
				</ESTADOS>

		</SPRITE>
		<SPRITE id="PlayerBlue" frameWidth="37" frameHeight="41">
				<ESTADOS cantidad="9">
					<ESTADO id="QUIETO-DER" cantFrames="3"/>
					<ESTADO id="CAMINA-DER" cantFrames="9"/>
					<ESTADO id="DESCONECTADO" cantFrames="1"/>
					<ESTADO id="AGACHADO" cantFrames="2"/>
					<ESTADO id="SALTANDO" cantFrames="3"/>
					<ESTADO id="CAMINA-IZQ" cantFrames="9"/>
					<ESTADO id="SALTANDO-DER" cantFrames="3"/>
					<ESTADO id="SALTANDO-IZQ" cantFrames="3"/>
					<ESTADO id="QUIETO-IZQ" cantFrames="3"/>
				</ESTADOS>

		</SPRITE>
		<SPRITE id="PlayerViolet" frameWidth="37" frameHeight="41">
				<ESTADOS cantidad="9">
					<ESTADO id="QUIETO-DER" cantFrames="3"/>
					<ESTADO id="CAMINA-DER" cantFrames="9"/>
					<ESTADO id="DESCONECTADO" cantFrames="1"/>
					<ESTADO id="AGACHADO" cantFrames="2"/>
					<ESTADO id="SALTANDO" cantFrames="3"/>
					<ESTADO id="CAMINA-IZQ" cantFrames="9"/>
					<ESTADO id="SALTANDO-DER" cantFrames="3"/>
					<ESTADO id="SALTANDO-IZQ" cantFrames="3"/>
					<ESTADO id="QUIETO-IZQ" cantFrames="3"/>
				</ESTADOS>
		</SPRITE>
		<SPRITE id="PulpoEnemigo" frameWidth="35" frameHeight="30">
			<ESTADOS cantidad="1">
				<ESTADO id="CAMINA-IZQ" cantFrames="16"/>
			</ESTADOS>
		</SPRITE>
		<SPRITE id="HumanoEnemigo" frameWidth="33" frameHeight="49">
			<ESTADOS cantidad="3">
				<ESTADO id="CAMINA-IZQ" cantFrames="10"/>
				<ESTADO id="DISPARA-IZQ" cantFrames="3"/>
				<ESTADO id="MUERTO" cantFrames="10"/>
			</ESTADOS>
		</SPRITE>
	</SPRITES>
</ESCENARIO>