<?xml version="1.0" encoding="UTF-8"?>
<ESCENARIO anchoPX="800" altoPX="600" maxJugadores="1">
	<FONDO>
		<CAPAS cantidad="3">
			<IMAGEN nombre="cieloLevel1.bmp" zIndex="2" width="2600" height="600"/>
			<IMAGEN nombre="plataformasLevel1.bmp" zIndex="1" width="2600" height="600"/>
			<IMAGEN nombre="pisoLevel1.bmp" zIndex="3" width="2600" height="600"/>
		</CAPAS>
	</FONDO>
	<SPRITES cantidad="13">
		<SPRITE id="PlayerRed-S" frameWidth="44" frameHeight="61" velocidad="100">
				<ESTADOS cantidad="16">
					<ESTADO id="QUIETO-DER" cantFrames="3"/>
					<ESTADO id="QUIETO-IZQ" cantFrames="3"/>
					<ESTADO id="CAMINA-DER" cantFrames="7"/>
					<ESTADO id="CAMINA-IZQ" cantFrames="7"/>
					<ESTADO id="SALTANDO-DER" cantFrames="4"/>
					<ESTADO id="SALTANDO-IZQ" cantFrames="4"/>
					<ESTADO id="QUIETO-DER-DISPARA" cantFrames="4"/>
					<ESTADO id="QUIETO-IZQ-DISPARA" cantFrames="4"/>
					<ESTADO id="DIAGONAL-DER" cantFrames="4"/>
					<ESTADO id="DIAGONAL-IZQ" cantFrames="4"/>
					<ESTADO id="ARRIBA-DER" cantFrames="2"/>
					<ESTADO id="ARRIBA-IZQ" cantFrames="2"/>
					<ESTADO id="ARRIBA-DER-DISPARA" cantFrames="4"/>
					<ESTADO id="ARRIBA-IZQ-DISPARA" cantFrames="4"/>
					<ESTADO id="DIAGONAL-DER-DISPARA" cantFrames="2"/>
					<ESTADO id="DIAGONAL-IZQ-DISPARA" cantFrames="2"/>
				</ESTADOS>
		</SPRITE>
		<SPRITE id="PlayerRed-H" frameWidth="44" frameHeight="61" velocidad="100">
				<ESTADOS cantidad="16">
					<ESTADO id="QUIETO-DER" cantFrames="3"/>
					<ESTADO id="QUIETO-IZQ" cantFrames="3"/>
					<ESTADO id="CAMINA-DER" cantFrames="7"/>
					<ESTADO id="CAMINA-IZQ" cantFrames="7"/>
					<ESTADO id="SALTANDO-DER" cantFrames="4"/>
					<ESTADO id="SALTANDO-IZQ" cantFrames="4"/>
					<ESTADO id="QUIETO-DER-DISPARA" cantFrames="4"/>
					<ESTADO id="QUIETO-IZQ-DISPARA" cantFrames="4"/>
					<ESTADO id="DIAGONAL-DER" cantFrames="4"/>
					<ESTADO id="DIAGONAL-IZQ" cantFrames="4"/>
					<ESTADO id="ARRIBA-DER" cantFrames="2"/>
					<ESTADO id="ARRIBA-IZQ" cantFrames="2"/>
					<ESTADO id="ARRIBA-DER-DISPARA" cantFrames="4"/>
					<ESTADO id="ARRIBA-IZQ-DISPARA" cantFrames="4"/>
					<ESTADO id="DIAGONAL-DER-DISPARA" cantFrames="2"/>
					<ESTADO id="DIAGONAL-IZQ-DISPARA" cantFrames="2"/>
				</ESTADOS>
		</SPRITE>
		<SPRITE id="PlayerRed-R" frameWidth="44" frameHeight="61" velocidad="100">
				<ESTADOS cantidad="16">
					<ESTADO id="QUIETO-DER" cantFrames="3"/>
					<ESTADO id="QUIETO-IZQ" cantFrames="3"/>
					<ESTADO id="CAMINA-DER" cantFrames="7"/>
					<ESTADO id="CAMINA-IZQ" cantFrames="7"/>
					<ESTADO id="SALTANDO-DER" cantFrames="4"/>
					<ESTADO id="SALTANDO-IZQ" cantFrames="4"/>
					<ESTADO id="QUIETO-DER-DISPARA" cantFrames="4"/>
					<ESTADO id="QUIETO-IZQ-DISPARA" cantFrames="4"/>
					<ESTADO id="DIAGONAL-DER" cantFrames="4"/>
					<ESTADO id="DIAGONAL-IZQ" cantFrames="4"/>
					<ESTADO id="ARRIBA-DER" cantFrames="2"/>
					<ESTADO id="ARRIBA-IZQ" cantFrames="2"/>
					<ESTADO id="ARRIBA-DER-DISPARA" cantFrames="4"/>
					<ESTADO id="ARRIBA-IZQ-DISPARA" cantFrames="4"/>
					<ESTADO id="DIAGONAL-DER-DISPARA" cantFrames="2"/>
					<ESTADO id="DIAGONAL-IZQ-DISPARA" cantFrames="2"/>
				</ESTADOS>
		</SPRITE>
		<SPRITE id="PlayerYellow-S" frameWidth="44" frameHeight="61" velocidad="200">
				<ESTADOS cantidad="16">
					<ESTADO id="QUIETO-DER" cantFrames="3"/>
					<ESTADO id="QUIETO-IZQ" cantFrames="3"/>
					<ESTADO id="CAMINA-DER" cantFrames="7"/>
					<ESTADO id="CAMINA-IZQ" cantFrames="7"/>
					<ESTADO id="SALTANDO-DER" cantFrames="4"/>
					<ESTADO id="SALTANDO-IZQ" cantFrames="4"/>
					<ESTADO id="QUIETO-DER-DISPARA" cantFrames="4"/>
					<ESTADO id="QUIETO-IZQ-DISPARA" cantFrames="4"/>
					<ESTADO id="DIAGONAL-DER" cantFrames="4"/>
					<ESTADO id="DIAGONAL-IZQ" cantFrames="4"/>
					<ESTADO id="ARRIBA-DER" cantFrames="2"/>
					<ESTADO id="ARRIBA-IZQ" cantFrames="2"/>
					<ESTADO id="ARRIBA-DER-DISPARA" cantFrames="4"/>
					<ESTADO id="ARRIBA-IZQ-DISPARA" cantFrames="4"/>
					<ESTADO id="DIAGONAL-DER-DISPARA" cantFrames="2"/>
					<ESTADO id="DIAGONAL-IZQ-DISPARA" cantFrames="2"/>
				</ESTADOS>
		</SPRITE>
		<SPRITE id="PlayerBlue" frameWidth="37" frameHeight="41" velocidad="200">
				<ESTADOS cantidad="9">
					<ESTADO id="QUIETO-DER" cantFrames="3"/>
					<ESTADO id="CAMINA-DER" cantFrames="9"/>
					<ESTADO id="DESCONECTADO" cantFrames="1"/>
					<ESTADO id="MUERTO" cantFrames="8"/>
					<ESTADO id="SALTANDO" cantFrames="3"/>
					<ESTADO id="CAMINA-IZQ" cantFrames="9"/>
					<ESTADO id="SALTANDO-DER" cantFrames="3"/>
					<ESTADO id="SALTANDO-IZQ" cantFrames="3"/>
					<ESTADO id="QUIETO-IZQ" cantFrames="3"/>
				</ESTADOS>

		</SPRITE>
		<SPRITE id="PlayerViolet" frameWidth="37" frameHeight="41" velocidad="200">
				<ESTADOS cantidad="9">
					<ESTADO id="QUIETO-DER" cantFrames="3"/>
					<ESTADO id="CAMINA-DER" cantFrames="9"/>
					<ESTADO id="DESCONECTADO" cantFrames="1"/>
					<ESTADO id="MUERTO" cantFrames="8"/>
					<ESTADO id="SALTANDO" cantFrames="3"/>
					<ESTADO id="CAMINA-IZQ" cantFrames="9"/>
					<ESTADO id="SALTANDO-DER" cantFrames="3"/>
					<ESTADO id="SALTANDO-IZQ" cantFrames="3"/>
					<ESTADO id="QUIETO-IZQ" cantFrames="3"/>
				</ESTADOS>
		</SPRITE>
		<SPRITE id="PulpoEnemigo" frameWidth="35" frameHeight="30" velocidad="100">
			<ESTADOS cantidad="1">
				<ESTADO id="CAMINA-IZQ" cantFrames="16"/>
			</ESTADOS>
		</SPRITE>
		<SPRITE id="HumanoEnemigo" frameWidth="33" frameHeight="49" velocidad="100">
			<ESTADOS cantidad="5">
				<ESTADO id="CAMINA-IZQ" cantFrames="10"/>
				<ESTADO id="DISPARA-IZQ" cantFrames="3"/>
				<ESTADO id="CAMINA-DER" cantFrames="10"/>
				<ESTADO id="DISPARA-DER" cantFrames="3"/>
				<ESTADO id="MUERTO" cantFrames="10"/>
			</ESTADOS>
		</SPRITE>
		<SPRITE id="TanqueEnemigo" frameWidth="106" frameHeight="62" velocidad="200">
				<ESTADOS cantidad="2">
					<ESTADO id="CAMINA-IZQ" cantFrames="2"/>
					<ESTADO id="DISPARA" cantFrames="3"/>
			</ESTADOS>
		</SPRITE>
		<SPRITE id="Bala-S" frameWidth="10" frameHeight="10" velocidad="100">
				<ESTADOS cantidad="4">
					<ESTADO id="HORIZONTAL" cantFrames="1"/>
					<ESTADO id="DIAGONAL-DER" cantFrames="1"/>
					<ESTADO id="VERTICAL" cantFrames="1"/>
					<ESTADO id="DIAGONAL-IZQ" cantFrames="1"/>
			</ESTADOS>
		</SPRITE>
		<SPRITE id="Bala-H" frameWidth="45" frameHeight="45" velocidad="150">
				<ESTADOS cantidad="5">
					<ESTADO id="HORIZONTAL-DER" cantFrames="1"/>
					<ESTADO id="HORIZONTAL-IZQ" cantFrames="1"/>
					<ESTADO id="DIAGONAL-DER" cantFrames="1"/>
					<ESTADO id="DIAGONAL-IZQ" cantFrames="1"/>
					<ESTADO id="VERTICAL" cantFrames="1"/>
			</ESTADOS>
		</SPRITE>
		<SPRITE id="Bala-R" frameWidth="64" frameHeight="64" velocidad="100">
				<ESTADOS cantidad="5">
					<ESTADO id="HORIZONTAL-DER" cantFrames="2"/>
					<ESTADO id="HORIZONTAL-IZQ" cantFrames="2"/>
					<ESTADO id="VERTICAL" cantFrames="2"/>
					<ESTADO id="DIAGONAL-DER" cantFrames="1"/>
					<ESTADO id="DIAGONAL-IZQ" cantFrames="1"/>
			</ESTADOS>
		</SPRITE>
		<SPRITE id="EnemigoFinal1" frameWidth="179" frameHeight="146" velocidad="100">
				<ESTADOS cantidad="3">
					<ESTADO id="CAMINA-IZQ" cantFrames="5"/>
					<ESTADO id="DISPARA" cantFrames="4"/>
					<ESTADO id="MUERTO" cantFrames="1"/>
			</ESTADOS>
		</SPRITE>
	</SPRITES>
	<NIVELES>
		<NIVEL id="Level_1">
			<ENEMIGOS cantidad="6">
				<ENEMIGO tipo="HumanoEnemigo" direccion="IZQ" posX="600" posY="390" vida="100" velocidadCaminata="5"/>
				<ENEMIGO tipo="HumanoEnemigo" direccion="IZQ" posX="450" posY="390" vida="100" velocidadCaminata="7"/>
				<ENEMIGO tipo="PulpoEnemigo" direccion="IZQ" posX="900" posY="390" vida="100" velocidadCaminata="12"/>
				<ENEMIGO tipo="TanqueEnemigo" direccion="IZQ" posX="530" posY="390" vida="100" velocidadCaminata="2"/>
				<ENEMIGO tipo="TanqueEnemigo" direccion="IZQ" posX="950" posY="390" vida="100" velocidadCaminata="3"/>
				<ENEMIGO tipo="EnemigoFinal1" direccion="IZQ" posX="2580" posY="150" vida="1000" velocidadCaminata="3"/>
			</ENEMIGOS>
		</NIVEL>
		<NIVEL id="Level_2">
			<ENEMIGOS cantidad="16">
				<ENEMIGO tipo="PulpoEnemigo" direccion="IZQ" posX="1200" posY="30" vida="100"/>
				<ENEMIGO tipo="TanqueEnemigo" direccion="DER" posX="1200" posY="15" vida="100"/>
				<ENEMIGO tipo="PulpoEnemigo" direccion="IZQ" posX="1200" posY="70" vida="100"/>
				<ENEMIGO tipo="TanqueEnemigo" direccion="DER" posX="1200" posY="110" vida="100"/>
				<ENEMIGO tipo="PulpoEnemigo" direccion="IZQ" posX="1200" posY="300" vida="100"/>
				<ENEMIGO tipo="PulpoEnemigo" direccion="DER" posX="1200" posY="530" vida="100"/>
				<ENEMIGO tipo="HumanoEnemigo" direccion="IZQ" posX="1200" posY="390" vida="100"/>
				<ENEMIGO tipo="TanqueEnemigo" direccion="DER" posX="1200" posY="700" vida="100"/>
				<ENEMIGO tipo="HumanoEnemigo" direccion="IZQ" posX="1200" posY="470" vida="100"/>
				<ENEMIGO tipo="PulpoEnemigo" direccion="DER" posX="1200" posY="420" vida="100"/>
				<ENEMIGO tipo="HumanoEnemigo" direccion="IZQ" posX="1200" posY="300" vida="100"/>
				<ENEMIGO tipo="PulpoEnemigo" direccion="DER" posX="1200" posY="530" vida="100"/>
				<ENEMIGO tipo="HumanoEnemigo" direccion="IZQ" posX="1200" posY="390" vida="100"/>
				<ENEMIGO tipo="TanqueEnemigo" direccion="DER" posX="1200" posY="700" vida="100"/>
				<ENEMIGO tipo="TanqueEnemigo" direccion="IZQ" posX="1200" posY="470" vida="100"/>
				<ENEMIGO tipo="Final" direccion="IZQ" posX="1200" posY="470" vida="700"/>
			</ENEMIGOS>
		</NIVEL>
		<NIVEL id="Level_3">
			<ENEMIGOS cantidad="21">
				<ENEMIGO tipo="PulpoEnemigo" direccion="IZQ" posX="1200" posY="30" vida="700"/>
				<ENEMIGO tipo="HumanoEnemigo" direccion="DER" posX="1200" posY="15" vida="700"/>
				<ENEMIGO tipo="TanqueEnemigo" direccion="IZQ" posX="1200" posY="70" vida="700"/>
				<ENEMIGO tipo="PulpoEnemigo" direccion="DER" posX="1200" posY="110" vida="700"/>
				<ENEMIGO tipo="HumanoEnemigo" direccion="IZQ" posX="1200" posY="300" vida="700"/>
				<ENEMIGO tipo="TanqueEnemigo" direccion="DER" posX="1200" posY="530" vida="700"/>
				<ENEMIGO tipo="HumanoEnemigo" direccion="IZQ" posX="1200" posY="390" vida="700"/>
				<ENEMIGO tipo="TanqueEnemigo" direccion="DER" posX="1200" posY="700" vida="700"/>
				<ENEMIGO tipo="HumanoEnemigo" direccion="IZQ" posX="1200" posY="470" vida="700"/>
				<ENEMIGO tipo="TanqueEnemigo" direccion="DER" posX="1200" posY="420" vida="700"/>
				<ENEMIGO tipo="HumanoEnemigo" direccion="IZQ" posX="1200" posY="30" vida="700"/>
				<ENEMIGO tipo="HumanoEnemigo" direccion="DER" posX="1200" posY="15" vida="700"/>
				<ENEMIGO tipo="PulpoEnemigo" direccion="IZQ" posX="1200" posY="70" vida="700"/>
				<ENEMIGO tipo="TanqueEnemigo" direccion="DER" posX="1200" posY="110" vida="700"/>
				<ENEMIGO tipo="HumanoEnemigo" direccion="IZQ" posX="1200" posY="300" vida="700"/>
				<ENEMIGO tipo="TanqueEnemigo" direccion="DER" posX="1200" posY="530" vida="700"/>
				<ENEMIGO tipo="PulpoEnemigo" direccion="IZQ" posX="1200" posY="390" vida="700"/>
				<ENEMIGO tipo="HumanoEnemigo" direccion="DER" posX="1200" posY="700" vida="700"/>
				<ENEMIGO tipo="TanqueEnemigo" direccion="IZQ" posX="1200" posY="470" vida="700"/>
				<ENEMIGO tipo="TanqueEnemigo" direccion="DER" posX="1200" posY="420" vida="700"/>
				<ENEMIGO tipo="Final" direccion="DER" posX="1200" posY="420" vida="1000"/>
			</ENEMIGOS>
		</NIVEL>
	</NIVELES>
</ESCENARIO>